infrahub_sdk/__init__.py
infrahub_sdk/_importer.py
infrahub_sdk/analyzer.py
infrahub_sdk/async_typer.py
infrahub_sdk/batch.py
infrahub_sdk/branch.py
infrahub_sdk/checks.py
infrahub_sdk/client.py
infrahub_sdk/config.py
infrahub_sdk/constants.py
infrahub_sdk/context.py
infrahub_sdk/convert_object_type.py
infrahub_sdk/data.py
infrahub_sdk/diff.py
infrahub_sdk/enums.py
infrahub_sdk/exceptions.py
infrahub_sdk/generator.py
infrahub_sdk/groups.py
infrahub_sdk/jinja2.py
infrahub_sdk/object_store.py
infrahub_sdk/operation.py
infrahub_sdk/playback.py
infrahub_sdk/protocols.py
infrahub_sdk/protocols_base.py
infrahub_sdk/queries.py
infrahub_sdk/query_groups.py
infrahub_sdk/recorder.py
infrahub_sdk/repository.py
infrahub_sdk/store.py
infrahub_sdk/timestamp.py
infrahub_sdk/topological_sort.py
infrahub_sdk/transforms.py
infrahub_sdk/types.py
infrahub_sdk/utils.py
infrahub_sdk/uuidt.py
infrahub_sdk/yaml.py
infrahub_sdk/ctl/AGENTS.md
infrahub_sdk/ctl/__init__.py
infrahub_sdk/ctl/branch.py
infrahub_sdk/ctl/check.py
infrahub_sdk/ctl/cli.py
infrahub_sdk/ctl/cli_commands.py
infrahub_sdk/ctl/client.py
infrahub_sdk/ctl/config.py
infrahub_sdk/ctl/exceptions.py
infrahub_sdk/ctl/exporter.py
infrahub_sdk/ctl/generator.py
infrahub_sdk/ctl/graphql.py
infrahub_sdk/ctl/importer.py
infrahub_sdk/ctl/menu.py
infrahub_sdk/ctl/object.py
infrahub_sdk/ctl/parameters.py
infrahub_sdk/ctl/render.py
infrahub_sdk/ctl/repository.py
infrahub_sdk/ctl/schema.py
infrahub_sdk/ctl/task.py
infrahub_sdk/ctl/transform.py
infrahub_sdk/ctl/utils.py
infrahub_sdk/ctl/validate.py
infrahub_sdk/graphql/__init__.py
infrahub_sdk/graphql/constants.py
infrahub_sdk/graphql/plugin.py
infrahub_sdk/graphql/query.py
infrahub_sdk/graphql/renderers.py
infrahub_sdk/graphql/utils.py
infrahub_sdk/node/__init__.py
infrahub_sdk/node/attribute.py
infrahub_sdk/node/constants.py
infrahub_sdk/node/metadata.py
infrahub_sdk/node/node.py
infrahub_sdk/node/parsers.py
infrahub_sdk/node/property.py
infrahub_sdk/node/related_node.py
infrahub_sdk-1.18.1.dist-info/METADATA
infrahub_sdk-1.18.1.dist-info/WHEEL
infrahub_sdk-1.18.1.dist-info/entry_points.txt
infrahub_sdk-1.18.1.dist-info/licenses/LICENSE.txt
infrahub_sdk-1.18.1.dist-info/RECORD
