Metadata-Version: 2.4
Name: infrahub-sdk
Version: 1.18.1
Summary: Python Client to interact with Infrahub
Project-URL: Homepage, https://opsmill.com
Project-URL: Repository, https://github.com/opsmill/infrahub-sdk-python
Project-URL: Documentation, https://docs.infrahub.app/python-sdk/introduction
Author-email: OpsMill <info@opsmill.com>
License: Apache-2.0
License-File: LICENSE.txt
Classifier: Intended Audience :: Developers
Classifier: Programming Language :: Python :: 3
Classifier: Programming Language :: Python :: 3.10
Classifier: Programming Language :: Python :: 3.11
Classifier: Programming Language :: Python :: 3.12
Classifier: Programming Language :: Python :: 3.13
Classifier: Programming Language :: Python :: 3.14
Requires-Python: <3.15,>=3.10
Requires-Dist: dulwich>=0.21.4
Requires-Dist: graphql-core<3.3,>=3.1
Requires-Dist: httpx>=0.20
Requires-Dist: netutils>=1.0.0
Requires-Dist: pydantic!=2.0.1,!=2.1.0,<3.0.0,>=2.0.0
Requires-Dist: pydantic-settings>=2.0
Requires-Dist: tomli>=1.1.0; python_version < '3.11'
Requires-Dist: ujson>=5
Requires-Dist: whenever<0.10.0,>=0.9.3
Provides-Extra: all
Requires-Dist: ariadne-codegen==0.15.3; extra == 'all'
Requires-Dist: click==8.1.*; extra == 'all'
Requires-Dist: jinja2>=3; extra == 'all'
Requires-Dist: numpy>=1.24.2; (python_version < '3.12') and extra == 'all'
Requires-Dist: numpy>=1.26.2; (python_version >= '3.12') and extra == 'all'
Requires-Dist: pyarrow>=14; extra == 'all'
Requires-Dist: pytest; extra == 'all'
Requires-Dist: pyyaml>=6; extra == 'all'
Requires-Dist: rich<14,>=12; extra == 'all'
Requires-Dist: typer>=0.12.5; extra == 'all'
Provides-Extra: ctl
Requires-Dist: ariadne-codegen==0.15.3; extra == 'ctl'
Requires-Dist: click==8.1.*; extra == 'ctl'
Requires-Dist: jinja2>=3; extra == 'ctl'
Requires-Dist: numpy>=1.24.2; (python_version < '3.12') and extra == 'ctl'
Requires-Dist: numpy>=1.26.2; (python_version >= '3.12') and extra == 'ctl'
Requires-Dist: pyarrow>=14; extra == 'ctl'
Requires-Dist: pyyaml>=6; extra == 'ctl'
Requires-Dist: rich<14,>=12; extra == 'ctl'
Requires-Dist: typer>=0.12.5; extra == 'ctl'
